{"cameraMode":{"drawMode":0,"name":"Shaded","section":"Shading Mode"},"sceneLighting":true,"audioPlay":false,"sceneViewState":{"m_AlwaysRefresh":false,"showFog":true,"showSkybox":true,"showFlares":true,"showImageEffects":true,"showParticleSystems":true,"showVisualEffectGraphs":true,"m_FxEnabled":true},"in2DMode":false,"pivot":{"x":714.0240478515625,"y":437.04229736328127,"z":-70.542236328125},"rotation":{"x":-0.03180481493473053,"y":-0.006899202708154917,"z":0.00022377027198672295,"w":-0.9994744062423706},"size":583.6322021484375,"orthographic":false}